[{
    "id": 1,
    "name": "Shakib Al Hasan",
    "email": "ssproat0@163.com",
    "gender": "Male",
    "image": "https://img1.hscicdn.com/image/upload/f_auto/lsci/db/PICTURES/CMS/296300/296315.6.jpg",
    "age": 34,
    "salary": 500000
  }, {
    "id": 2,
    "name": "Mashrafe Mortaza",
    "email": "rkramer1@exblog.jp",
    "gender": "Male",
    "image": "https://cdn.dnaindia.com/sites/default/files/styles/full/public/2018/12/30/771982-mashrafe-mortaza.jpg",
    "age": 37,
    "salary": 500000
  }, {
    "id": 3,
    "name": "Musfiqur Rahim",
    "email": "kschrieves2@bloglovin.com",
    "gender": "Male",
    "image": "https://akm-img-a-in.tosshub.com/indiatoday/images/story/201910/mushi27102019.jpeg?_R6oH_Or1toiybdjhLfA8yqxlaksx2Hy&size=770:433",
    "age": 34,
    "salary": 500000
  }, {
    "id": 4,
    "name": "Mahmudullah",
    "email": "mtoffano3@dell.com",
    "gender": "Male",
    "image": "https://www.cricketcountry.com/wp-content/uploads/2018/10/Mahmudullah-Getty-Images.jpg",
    "age": 35,
    "salary": 500000
  }, {
    "id": 5,
    "name": "Tamim Iqbal",
    "email": "mspratling4@hubpages.com",
    "gender": "Male",
    "image": "https://c.ndtvimg.com/2020-03/uejheitg_tamim-iqbal-afp_625x300_08_March_20.jpg",
    "age": 32,
    "salary": 500000
  }, {
    "id": 6,
    "name": "Soumya Sarkar",
    "email": "norts5@people.com.cn",
    "gender": "Male",
    "image": "https://www.indiafantasy.com/wp-content/uploads/Untitled-design-4-3.jpg",
    "age": 28,
    "salary": 500000
  }, {
    "id": 7,
    "name": "Mehidy Hasan",
    "email": "mlogsdail6@wufoo.com",
    "gender": "Male",
    "image": "https://staticg.sportskeeda.com/editor/2021/02/1a8ed-16144961536755-800.jpg",
    "age": 23,
    "salary": 500000
  }, {
    "id": 8,
    "name": "Mustafizur Rahman",
    "email": "jandrzejowski7@businessweek.com",
    "gender": "Male",
    "image": "https://www.cricketsoccer.com/wp-content/uploads/2018/09/280728.jpg",
    "age": 25,
    "salary": 500000
  }, {
    "id": 9,
    "name": "Taskin Ahmed",
    "email": "estiegers8@nba.com",
    "gender": "Male",
    "image": "https://p.imgci.com/db/PICTURES/CMS/252900/252917.jpg",
    "age": 26,
    "salary": 500000
  }, {
    "id": 10,
    "name": "Nasir Khan",
    "email": "fbremmell9@alibaba.com",
    "gender": "Male",
    "image": "https://www.bdcrictime.com/wp-content/uploads/2017/01/BCB-to-Nasir-Al-Amin-from-central-contracts.jpg",
    "age": 29,
    "salary": 500000
  }, {
    "id": 11,
    "name": "Imrul Kayes",
    "email": "ktivnana@dion.ne.jp",
    "gender": "Male",
    "image": "https://www.bdcrictime.com/wp-content/uploads/2020/03/imrul-bro.jpg",
    "age": 34,
    "salary": 500000
  }, {
    "id": 12,
    "name": "Sabbir Rahman",
    "email": "aakhurstb@google.nl",
    "gender": "Male",
    "image": "http://www.dainikocean.com/en/files/uploads/Sabbir-Rahman-dedicated-his-first-century-to-his-p.jpg",
    "age": 29,
    "salary": 500000
  }, {
    "id": 13,
    "name": "Rubel Hossain",
    "email": "ezanucioliic@prweb.com",
    "gender": "Male",
    "image": "https://www.cricketcountry.com/wp-content/uploads/2015/05/Rubel-Hossain-of-Bangladesh-appeals-for-a-wicket-21.jpg",
    "age": 31,
    "salary": 500000
  }, {
    "id": 14,
    "name": "Soumya Sarkar",
    "email": "qlammertd@ox.ac.uk",
    "gender": "Male",
    "image": "https://www.indiafantasy.com/wp-content/uploads/Untitled-design-4-3.jpg",
    "age": 28,
    "salary": 500000
  }, {
    "id": 15,
    "name": "Liton Das",
    "email": "gsullense@uol.com.br",
    "gender": "Male",
    "image": "https://resources.pulse.icc-cricket.com/ICC/photo/2018/10/17/cf0e9cc5-02a3-4a7a-8e93-4ad46d08ec82/Liton-Das.jpg",
    "age": 27,
    "salary": 500000
  }]